dimstack/__init__.py
dimstack/calc.py
dimstack/dim.py
dimstack/display.py
dimstack/dist.py
dimstack/plot.py
dimstack/stats.py
dimstack/tolerance.py
dimstack/utils.py
dimstack-0.8.0.dist-info/METADATA
dimstack-0.8.0.dist-info/WHEEL
dimstack-0.8.0.dist-info/RECORD
