Metadata-Version: 2.4
Name: dimstack
Version: 0.8.0
Author-email: phcreery <phcreery@gmail.com>
License: MIT
Requires-Python: >=3.8
Requires-Dist: jinja2>=3.1.2
Requires-Dist: pandas>=1.5.2
Requires-Dist: plotly>=5.14.1
Requires-Dist: rich>=13.7.0
Requires-Dist: scipy>=1.8.1
